modelparameters/__init__.py
modelparameters/codegeneration.py
modelparameters/commands.py
modelparameters/config.py
modelparameters/logger.py
modelparameters/parameterdict.py
modelparameters/parameters.py
modelparameters/sympytools.py
modelparameters/utils.py
modelparameters/sympy/__init__.py
modelparameters/sympy/abc.py
modelparameters/sympy/galgebra.py
modelparameters/sympy/release.py
modelparameters/sympy/assumptions/__init__.py
modelparameters/sympy/assumptions/ask.py
modelparameters/sympy/assumptions/ask_generated.py
modelparameters/sympy/assumptions/assume.py
modelparameters/sympy/assumptions/refine.py
modelparameters/sympy/assumptions/satask.py
modelparameters/sympy/assumptions/sathandlers.py
modelparameters/sympy/assumptions/handlers/__init__.py
modelparameters/sympy/assumptions/handlers/calculus.py
modelparameters/sympy/assumptions/handlers/common.py
modelparameters/sympy/assumptions/handlers/matrices.py
modelparameters/sympy/assumptions/handlers/ntheory.py
modelparameters/sympy/assumptions/handlers/order.py
modelparameters/sympy/assumptions/handlers/sets.py
modelparameters/sympy/calculus/__init__.py
modelparameters/sympy/calculus/euler.py
modelparameters/sympy/calculus/finite_diff.py
modelparameters/sympy/calculus/singularities.py
modelparameters/sympy/calculus/util.py
modelparameters/sympy/categories/__init__.py
modelparameters/sympy/categories/baseclasses.py
modelparameters/sympy/categories/diagram_drawing.py
modelparameters/sympy/codegen/__init__.py
modelparameters/sympy/codegen/ast.py
modelparameters/sympy/codegen/cfunctions.py
modelparameters/sympy/codegen/ffunctions.py
modelparameters/sympy/combinatorics/__init__.py
modelparameters/sympy/combinatorics/fp_groups.py
modelparameters/sympy/combinatorics/free_groups.py
modelparameters/sympy/combinatorics/generators.py
modelparameters/sympy/combinatorics/graycode.py
modelparameters/sympy/combinatorics/group_constructs.py
modelparameters/sympy/combinatorics/named_groups.py
modelparameters-2023.1.0.dist-info/LICENSE
modelparameters-2023.1.0.dist-info/LICENSE_sympy
modelparameters-2023.1.0.dist-info/METADATA
modelparameters-2023.1.0.dist-info/WHEEL
modelparameters-2023.1.0.dist-info/top_level.txt
modelparameters-2023.1.0.dist-info/RECORD
