Metadata-Version: 2.1
Name: modelparameters
Version: 2023.1.0
Summary: A module providing parameter structure for physical modeling
Home-page: https://github.com/ComputationalPhysiology/modelparameters
Author: Johan Hake, Henrik Finsberg, Kristian G Hustad
Author-email: henriknf@simula.no
License: LGPL-3.0
Keywords: ODE,solver,system,equations,cuda
Classifier: License :: OSI Approved :: GNU Lesser General Public License v3 (LGPLv3)
Classifier: Programming Language :: Python :: 3
Classifier: Programming Language :: Python :: 3 :: Only
Classifier: Programming Language :: Python :: Implementation :: CPython
Requires-Python: >=3.7
License-File: LICENSE_sympy
License-File: LICENSE
Requires-Dist: mpmath
Requires-Dist: numpy
Requires-Dist: pint
Provides-Extra: dev
Requires-Dist: black ; extra == 'dev'
Requires-Dist: bump2version ; extra == 'dev'
Requires-Dist: flake8 ; extra == 'dev'
Requires-Dist: ipython ; extra == 'dev'
Requires-Dist: isort ; extra == 'dev'
Requires-Dist: mypy ; extra == 'dev'
Requires-Dist: pdbpp ; extra == 'dev'
Requires-Dist: pip ; extra == 'dev'
Requires-Dist: pre-commit ; extra == 'dev'
Requires-Dist: twine ; extra == 'dev'
Requires-Dist: wheel ; extra == 'dev'
Provides-Extra: doc
Requires-Dist: Sphinx ; extra == 'doc'
Requires-Dist: pandoc ; extra == 'doc'
Requires-Dist: sphinx-rtd-theme ; extra == 'doc'
Provides-Extra: test
Requires-Dist: pytest ; extra == 'test'
Requires-Dist: pytest-cov ; extra == 'test'
